pydataimport/__init__.py
pydataimport/__pycache__/__init__.cpython-310.pyc
pydataimport/config/db_config.py
pydataimport/config/env_config.py
pydataimport/config/__pycache__/db_config.cpython-310.pyc
pydataimport/config/__pycache__/env_config.cpython-310.pyc
pydataimport/models/__init__.py
pydataimport/models/api_source.py
pydataimport/models/__pycache__/__init__.cpython-310.pyc
pydataimport/models/__pycache__/api_source.cpython-310.pyc
pydataimport/services/__init__.py
pydataimport/services/__pycache__/__init__.cpython-310.pyc
pydataimport/services/data_import/__init__.py
pydataimport/services/data_import/data_import_service.py
pydataimport/services/data_import/__pycache__/__init__.cpython-310.pyc
pydataimport/services/data_import/__pycache__/data_import_service.cpython-310.pyc
pydataimport/services/db/__init__.py
pydataimport/services/db/data_storage_query_service.py
pydataimport/services/db/data_storage_service.py
pydataimport/services/db/datatype_service.py
pydataimport/services/db/storage_service.py
pydataimport/services/db/__pycache__/__init__.cpython-310.pyc
pydataimport/services/db/__pycache__/data_storage_query_service.cpython-310.pyc
pydataimport/services/db/__pycache__/data_storage_service.cpython-310.pyc
pydataimport/services/db/__pycache__/datatype_service.cpython-310.pyc
pydataimport/services/db/__pycache__/storage_service.cpython-310.pyc
pydataimport/services/fetch/__init__.py
pydataimport/services/fetch/data_fetch_service.py
pydataimport/services/fetch/__pycache__/__init__.cpython-310.pyc
pydataimport/services/fetch/__pycache__/data_fetch_service.cpython-310.pyc
pydataimport/services/file/__init__.py
pydataimport/services/file/file_service.py
pydataimport/services/file/__pycache__/__init__.cpython-310.pyc
pydataimport/services/file/__pycache__/file_service.cpython-310.pyc
pydataimport/services/log/__init__.py
pydataimport/services/log/log_service.py
pydataimport/services/log/__pycache__/__init__.cpython-310.pyc
pydataimport-0.1.2.dist-info/METADATA
pydataimport-0.1.2.dist-info/WHEEL
pydataimport-0.1.2.dist-info/top_level.txt
pydataimport-0.1.2.dist-info/RECORD
